nonebot_args_patch/__init__.py
nonebot_args_patch/args.py
nonebot_args_patch/commandarg.py
nonebot_args_patch/consts.py
nonebot_args_patch/exception.py
nonebot_args_patch/helper.py
nonebot_args_patch/patch.py
nonebot_args_patch/provider.py
nonebot_args_patch/rule.py
nonebot_args_patch-0.3.0.dist-info/LICENSE
nonebot_args_patch-0.3.0.dist-info/METADATA
nonebot_args_patch-0.3.0.dist-info/WHEEL
nonebot_args_patch-0.3.0.dist-info/top_level.txt
nonebot_args_patch-0.3.0.dist-info/RECORD
